earthkit/time/__init__.py
earthkit/time/calendar.py
earthkit/time/climatology.py
earthkit/time/sequence.py
earthkit/time/utilities.py
earthkit/time/cli/__init__.py
earthkit/time/cli/actions.py
earthkit/time/cli/cliargs.py
earthkit/time/cli/climatology.py
earthkit/time/cli/cliout.py
earthkit/time/cli/date.py
earthkit/time/cli/sequence.py
earthkit/time/data/__init__.py
earthkit/time/data/sequences/__init__.py
earthkit/time/data/sequences/ecmwf-2days.yaml
earthkit/time/data/sequences/ecmwf-4days.yaml
earthkit/time/data/sequences/ecmwf-mon-thu.yaml
earthkit_time-0.1.7.dist-info/LICENSE
earthkit_time-0.1.7.dist-info/METADATA
earthkit_time-0.1.7.dist-info/WHEEL
earthkit_time-0.1.7.dist-info/entry_points.txt
earthkit_time-0.1.7.dist-info/top_level.txt
earthkit_time-0.1.7.dist-info/RECORD
