Metadata-Version: 2.1
Name: earthkit-time
Version: 0.1.7
Summary: Date and time manipulation routines for the use of weather data
License:                                  Apache License
Project-URL: Homepage, https://github.com/ecmwf/earthkit-time/
Project-URL: Documentation, https://earthkit-time.readthedocs.io
Classifier: Development Status :: 4 - Beta
Classifier: Intended Audience :: Science/Research
Classifier: License :: OSI Approved :: Apache Software License
Classifier: Natural Language :: English
Classifier: Operating System :: OS Independent
Classifier: Programming Language :: Python :: 3
Classifier: Programming Language :: Python :: 3 :: Only
Classifier: Programming Language :: Python :: 3.8
Classifier: Programming Language :: Python :: 3.9
Classifier: Programming Language :: Python :: 3.10
Classifier: Programming Language :: Python :: 3.11
Classifier: Programming Language :: Python :: 3.12
Classifier: Programming Language :: Python :: 3.13
Classifier: Topic :: Scientific/Engineering
Requires-Python: >=3.8
License-File: LICENSE
Requires-Dist: pyyaml
Provides-Extra: docs
Requires-Dist: myst-parser; extra == "docs"
Requires-Dist: Sphinx; extra == "docs"
Requires-Dist: sphinx-rtd-theme; extra == "docs"
Provides-Extra: test
Requires-Dist: pytest>=8.1; extra == "test"
